{"1": [{"time": "2019/07/16 - 08:40:26", "temp": 2, "hum": 34}, {"time": "2019/07/16 - 08:40:35", "temp": 10, "hum": 55}, {"time": "2019/07/16 - 08:40:37", "temp": 5, "hum": 44}, {"time": "2019/07/16 - 08:40:38", "temp": -8, "hum": 52}, {"time": "2019/07/16 - 08:47:58", "temp": 23, "hum": 60}, {"time": "2019/07/16 - 10:02:57", "temp": 8, "hum": 18}, {"time": "2019/07/16 - 10:02:57", "temp": 6, "hum": 87}, {"time": "2019/07/16 - 10:02:57", "temp": 18, "hum": 91}, {"time": "2019/07/16 - 10:02:57", "temp": 36, "hum": 41}, {"time": "2019/07/16 - 10:02:57", "temp": 15, "hum": 95}, {"time": "2019/07/16 - 10:28:15", "temp": 22, "hum": 68}, {"time": "2019/07/16 - 10:28:15", "temp": 21, "hum": 27}, {"time": "2019/07/16 - 10:28:15", "temp": 7, "hum": 66}, {"time": "2019/07/16 - 10:28:15", "temp": 19, "hum": 70}, {"time": "2019/07/16 - 10:28:15", "temp": 41, "hum": 45}, {"time": "2019/07/16 - 11:16:05", "temp": 15, "hum": 33}, {"time": "2019/07/16 - 11:16:05", "temp": 5, "hum": 71}, {"time": "2019/07/16 - 11:16:05", "temp": 21, "hum": 31}, {"time": "2019/07/16 - 11:16:05", "temp": 42, "hum": 65}, {"time": "2019/07/16 - 11:16:05", "temp": 37, "hum": 40}], "2": [{"time": "2019/07/16 - 08:40:26", "temp": -9, "hum": 29}, {"time": "2019/07/16 - 08:40:35", "temp": 12, "hum": 12}, {"time": "2019/07/16 - 08:40:37", "temp": -4, "hum": 18}, {"time": "2019/07/16 - 08:40:38", "temp": 16, "hum": 44}, {"time": "2019/07/16 - 08:47:58", "temp": 15, "hum": 17}, {"time": "2019/07/16 - 10:02:57", "temp": 4, "hum": 78}, {"time": "2019/07/16 - 10:02:57", "temp": 8, "hum": 20}, {"time": "2019/07/16 - 10:02:57", "temp": -9, "hum": 7}, {"time": "2019/07/16 - 10:02:57", "temp": 16, "hum": 53}, {"time": "2019/07/16 - 10:02:57", "temp": 16, "hum": 92}, {"time": "2019/07/16 - 10:28:15", "temp": 50, "hum": 55}, {"time": "2019/07/16 - 10:28:15", "temp": 40, "hum": 34}, {"time": "2019/07/16 - 10:28:15", "temp": -8, "hum": 6}, {"time": "2019/07/16 - 10:28:15", "temp": 4, "hum": 53}, {"time": "2019/07/16 - 10:28:15", "temp": 13, "hum": 44}, {"time": "2019/07/16 - 11:16:05", "temp": -4, "hum": 25}, {"time": "2019/07/16 - 11:16:05", "temp": -8, "hum": 49}, {"time": "2019/07/16 - 11:16:05", "temp": 20, "hum": 11}, {"time": "2019/07/16 - 11:16:06", "temp": 12, "hum": 33}, {"time": "2019/07/16 - 11:16:06", "temp": 42, "hum": 20}], "3": [{"time": "2019/07/16 - 08:40:26", "temp": 21, "hum": 42}, {"time": "2019/07/16 - 08:40:35", "temp": 37, "hum": 26}, {"time": "2019/07/16 - 08:40:37", "temp": -8, "hum": 72}, {"time": "2019/07/16 - 08:40:38", "temp": 7, "hum": 13}, {"time": "2019/07/16 - 08:47:58", "temp": 17, "hum": 4}, {"time": "2019/07/16 - 10:02:57", "temp": 20, "hum": 97}, {"time": "2019/07/16 - 10:02:57", "temp": 31, "hum": 92}, {"time": "2019/07/16 - 10:02:57", "temp": -6, "hum": 78}, {"time": "2019/07/16 - 10:02:57", "temp": 6, "hum": 82}, {"time": "2019/07/16 - 10:02:57", "temp": 2, "hum": 25}, {"time": "2019/07/16 - 10:28:15", "temp": -6, "hum": 5}, {"time": "2019/07/16 - 10:28:15", "temp": 15, "hum": 39}, {"time": "2019/07/16 - 10:28:15", "temp": -7, "hum": 94}, {"time": "2019/07/16 - 10:28:15", "temp": 36, "hum": 26}, {"time": "2019/07/16 - 10:28:16", "temp": -6, "hum": 4}, {"time": "2019/07/16 - 11:16:06", "temp": 27, "hum": 48}, {"time": "2019/07/16 - 11:16:06", "temp": 7, "hum": 21}, {"time": "2019/07/16 - 11:16:06", "temp": 10, "hum": 49}, {"time": "2019/07/16 - 11:16:06", "temp": 43, "hum": 17}, {"time": "2019/07/16 - 11:16:06", "temp": 7, "hum": 18}], "4": [{"time": "2019/07/16 - 08:40:26", "temp": 33, "hum": 99}, {"time": "2019/07/16 - 08:40:35", "temp": 14, "hum": 21}, {"time": "2019/07/16 - 08:40:37", "temp": 4, "hum": 43}, {"time": "2019/07/16 - 08:40:38", "temp": -2, "hum": 89}, {"time": "2019/07/16 - 08:47:58", "temp": 29, "hum": 50}, {"time": "2019/07/16 - 10:02:57", "temp": 40, "hum": 32}, {"time": "2019/07/16 - 10:02:57", "temp": 10, "hum": 75}, {"time": "2019/07/16 - 10:02:57", "temp": -1, "hum": 26}, {"time": "2019/07/16 - 10:02:58", "temp": 9, "hum": 70}, {"time": "2019/07/16 - 10:02:58", "temp": -1, "hum": 23}, {"time": "2019/07/16 - 10:28:16", "temp": 25, "hum": 74}, {"time": "2019/07/16 - 10:28:16", "temp": 50, "hum": 94}, {"time": "2019/07/16 - 10:28:16", "temp": 46, "hum": 90}, {"time": "2019/07/16 - 10:28:16", "temp": 23, "hum": 66}, {"time": "2019/07/16 - 10:28:16", "temp": -7, "hum": 58}, {"time": "2019/07/16 - 11:16:06", "temp": 33, "hum": 90}, {"time": "2019/07/16 - 11:16:06", "temp": 4, "hum": 97}, {"time": "2019/07/16 - 11:16:06", "temp": 45, "hum": 49}, {"time": "2019/07/16 - 11:16:06", "temp": 14, "hum": 97}, {"time": "2019/07/16 - 11:16:06", "temp": 21, "hum": 31}], "5": [{"time": "2019/07/16 - 08:40:26", "temp": 24, "hum": 61}, {"time": "2019/07/16 - 08:40:35", "temp": 39, "hum": 63}, {"time": "2019/07/16 - 08:40:37", "temp": -10, "hum": 80}, {"time": "2019/07/16 - 08:40:38", "temp": 1, "hum": 95}, {"time": "2019/07/16 - 08:47:58", "temp": -2, "hum": 15}, {"time": "2019/07/16 - 10:02:58", "temp": 16, "hum": 87}, {"time": "2019/07/16 - 10:02:58", "temp": 41, "hum": 0}, {"time": "2019/07/16 - 10:02:58", "temp": 0, "hum": 74}, {"time": "2019/07/16 - 10:02:58", "temp": 45, "hum": 80}, {"time": "2019/07/16 - 10:02:58", "temp": -3, "hum": 65}, {"time": "2019/07/16 - 10:28:16", "temp": 21, "hum": 85}, {"time": "2019/07/16 - 10:28:16", "temp": 33, "hum": 75}, {"time": "2019/07/16 - 10:28:16", "temp": 26, "hum": 46}, {"time": "2019/07/16 - 10:28:16", "temp": 16, "hum": 36}, {"time": "2019/07/16 - 10:28:16", "temp": 20, "hum": 99}, {"time": "2019/07/16 - 11:16:06", "temp": 10, "hum": 30}, {"time": "2019/07/16 - 11:16:06", "temp": 14, "hum": 91}, {"time": "2019/07/16 - 11:16:06", "temp": -10, "hum": 97}, {"time": "2019/07/16 - 11:16:06", "temp": 31, "hum": 85}, {"time": "2019/07/16 - 11:16:06", "temp": 7, "hum": 64}], "6": [{"time": "2019/07/16 - 08:40:26", "temp": 21, "hum": 61}, {"time": "2019/07/16 - 08:40:35", "temp": 1, "hum": 15}, {"time": "2019/07/16 - 08:40:37", "temp": 19, "hum": 100}, {"time": "2019/07/16 - 08:40:39", "temp": 29, "hum": 8}, {"time": "2019/07/16 - 08:47:59", "temp": 30, "hum": 100}, {"time": "2019/07/16 - 10:02:58", "temp": -2, "hum": 60}, {"time": "2019/07/16 - 10:02:58", "temp": 6, "hum": 85}, {"time": "2019/07/16 - 10:02:58", "temp": 11, "hum": 68}, {"time": "2019/07/16 - 10:02:58", "temp": 12, "hum": 61}, {"time": "2019/07/16 - 10:02:58", "temp": -5, "hum": 42}, {"time": "2019/07/16 - 10:28:16", "temp": 43, "hum": 15}, {"time": "2019/07/16 - 10:28:16", "temp": 32, "hum": 10}, {"time": "2019/07/16 - 10:28:16", "temp": -10, "hum": 96}, {"time": "2019/07/16 - 10:28:16", "temp": 13, "hum": 9}, {"time": "2019/07/16 - 10:28:16", "temp": -8, "hum": 39}, {"time": "2019/07/16 - 11:16:06", "temp": 50, "hum": 10}, {"time": "2019/07/16 - 11:16:06", "temp": -6, "hum": 94}, {"time": "2019/07/16 - 11:16:06", "temp": 33, "hum": 90}, {"time": "2019/07/16 - 11:16:07", "temp": 7, "hum": 80}, {"time": "2019/07/16 - 11:16:07", "temp": 3, "hum": 21}], "7": [{"time": "2019/07/16 - 08:40:26", "temp": 36, "hum": 9}, {"time": "2019/07/16 - 08:40:35", "temp": -4, "hum": 30}, {"time": "2019/07/16 - 08:40:37", "temp": 18, "hum": 61}, {"time": "2019/07/16 - 08:40:39", "temp": 33, "hum": 96}, {"time": "2019/07/16 - 08:47:59", "temp": 14, "hum": 9}, {"time": "2019/07/16 - 10:02:58", "temp": 26, "hum": 19}, {"time": "2019/07/16 - 10:02:58", "temp": -4, "hum": 66}, {"time": "2019/07/16 - 10:02:58", "temp": -8, "hum": 42}, {"time": "2019/07/16 - 10:02:58", "temp": -8, "hum": 87}, {"time": "2019/07/16 - 10:02:58", "temp": -5, "hum": 69}, {"time": "2019/07/16 - 10:28:16", "temp": 12, "hum": 8}, {"time": "2019/07/16 - 10:28:17", "temp": 42, "hum": 83}, {"time": "2019/07/16 - 10:28:17", "temp": 30, "hum": 43}, {"time": "2019/07/16 - 10:28:17", "temp": 34, "hum": 33}, {"time": "2019/07/16 - 10:28:17", "temp": 46, "hum": 82}, {"time": "2019/07/16 - 11:16:07", "temp": 7, "hum": 87}, {"time": "2019/07/16 - 11:16:07", "temp": 28, "hum": 55}, {"time": "2019/07/16 - 11:16:07", "temp": -10, "hum": 74}, {"time": "2019/07/16 - 11:16:07", "temp": 7, "hum": 78}, {"time": "2019/07/16 - 11:16:07", "temp": -4, "hum": 44}], "8": [{"time": "2019/07/16 - 08:40:26", "temp": 8, "hum": 17}, {"time": "2019/07/16 - 08:40:35", "temp": 8, "hum": 95}, {"time": "2019/07/16 - 08:40:37", "temp": 23, "hum": 69}, {"time": "2019/07/16 - 08:40:39", "temp": 30, "hum": 22}, {"time": "2019/07/16 - 08:47:59", "temp": 5, "hum": 67}, {"time": "2019/07/16 - 10:02:58", "temp": 23, "hum": 2}, {"time": "2019/07/16 - 10:02:58", "temp": 5, "hum": 8}, {"time": "2019/07/16 - 10:02:58", "temp": 11, "hum": 36}, {"time": "2019/07/16 - 10:02:59", "temp": 28, "hum": 27}, {"time": "2019/07/16 - 10:02:59", "temp": 12, "hum": 92}, {"time": "2019/07/16 - 10:28:17", "temp": 6, "hum": 30}, {"time": "2019/07/16 - 10:28:17", "temp": 37, "hum": 34}, {"time": "2019/07/16 - 10:28:17", "temp": 13, "hum": 42}, {"time": "2019/07/16 - 10:28:17", "temp": 38, "hum": 5}, {"time": "2019/07/16 - 10:28:17", "temp": 47, "hum": 87}, {"time": "2019/07/16 - 11:16:07", "temp": 12, "hum": 14}, {"time": "2019/07/16 - 11:16:07", "temp": 7, "hum": 8}, {"time": "2019/07/16 - 11:16:07", "temp": -4, "hum": 78}, {"time": "2019/07/16 - 11:16:07", "temp": 45, "hum": 7}, {"time": "2019/07/16 - 11:16:07", "temp": 24, "hum": 6}], "9": [{"time": "2019/07/16 - 08:40:26", "temp": -1, "hum": 55}, {"time": "2019/07/16 - 08:40:35", "temp": 7, "hum": 70}, {"time": "2019/07/16 - 08:40:37", "temp": -4, "hum": 58}, {"time": "2019/07/16 - 08:40:39", "temp": 9, "hum": 56}, {"time": "2019/07/16 - 08:47:59", "temp": 7, "hum": 0}, {"time": "2019/07/16 - 10:02:59", "temp": 42, "hum": 49}, {"time": "2019/07/16 - 10:02:59", "temp": -4, "hum": 11}, {"time": "2019/07/16 - 10:02:59", "temp": 47, "hum": 69}, {"time": "2019/07/16 - 10:02:59", "temp": -7, "hum": 92}, {"time": "2019/07/16 - 10:02:59", "temp": 35, "hum": 15}, {"time": "2019/07/16 - 10:28:17", "temp": 35, "hum": 22}, {"time": "2019/07/16 - 10:28:17", "temp": 24, "hum": 72}, {"time": "2019/07/16 - 10:28:17", "temp": 50, "hum": 70}, {"time": "2019/07/16 - 10:28:17", "temp": -6, "hum": 15}, {"time": "2019/07/16 - 10:28:17", "temp": 48, "hum": 49}, {"time": "2019/07/16 - 11:16:07", "temp": 31, "hum": 95}, {"time": "2019/07/16 - 11:16:07", "temp": 14, "hum": 96}, {"time": "2019/07/16 - 11:16:08", "temp": 4, "hum": 51}, {"time": "2019/07/16 - 11:16:08", "temp": -9, "hum": 25}, {"time": "2019/07/16 - 11:16:08", "temp": 20, "hum": 100}], "10": [{"time": "2019/07/16 - 08:40:26", "temp": 40, "hum": 89}, {"time": "2019/07/16 - 08:40:35", "temp": 30, "hum": 71}, {"time": "2019/07/16 - 08:40:37", "temp": 27, "hum": 54}, {"time": "2019/07/16 - 08:40:39", "temp": 39, "hum": 100}, {"time": "2019/07/16 - 08:47:59", "temp": 37, "hum": 65}, {"time": "2019/07/16 - 10:02:59", "temp": 49, "hum": 68}, {"time": "2019/07/16 - 10:02:59", "temp": 29, "hum": 56}, {"time": "2019/07/16 - 10:02:59", "temp": -2, "hum": 90}, {"time": "2019/07/16 - 10:02:59", "temp": 18, "hum": 21}, {"time": "2019/07/16 - 10:02:59", "temp": 36, "hum": 87}, {"time": "2019/07/16 - 10:28:17", "temp": -9, "hum": 45}, {"time": "2019/07/16 - 10:28:17", "temp": 0, "hum": 94}, {"time": "2019/07/16 - 10:28:17", "temp": 42, "hum": 51}, {"time": "2019/07/16 - 10:28:17", "temp": 16, "hum": 14}, {"time": "2019/07/16 - 10:28:17", "temp": 46, "hum": 81}, {"time": "2019/07/16 - 11:16:08", "temp": 46, "hum": 68}, {"time": "2019/07/16 - 11:16:08", "temp": 50, "hum": 49}, {"time": "2019/07/16 - 11:16:08", "temp": 13, "hum": 67}, {"time": "2019/07/16 - 11:16:08", "temp": 1, "hum": 48}, {"time": "2019/07/16 - 11:16:08", "temp": 4, "hum": 45}], "11": [{"time": "2019/07/16 - 08:40:26", "temp": -3, "hum": 67}, {"time": "2019/07/16 - 08:40:35", "temp": 39, "hum": 74}, {"time": "2019/07/16 - 08:40:37", "temp": 50, "hum": 50}, {"time": "2019/07/16 - 08:40:39", "temp": 43, "hum": 70}, {"time": "2019/07/16 - 08:47:59", "temp": 49, "hum": 55}, {"time": "2019/07/16 - 10:02:59", "temp": -2, "hum": 55}, {"time": "2019/07/16 - 10:02:59", "temp": 32, "hum": 13}, {"time": "2019/07/16 - 10:02:59", "temp": 38, "hum": 37}, {"time": "2019/07/16 - 10:02:59", "temp": -10, "hum": 71}, {"time": "2019/07/16 - 10:02:59", "temp": 38, "hum": 3}, {"time": "2019/07/16 - 10:28:18", "temp": 25, "hum": 53}, {"time": "2019/07/16 - 10:28:18", "temp": 12, "hum": 31}, {"time": "2019/07/16 - 10:28:18", "temp": 38, "hum": 51}, {"time": "2019/07/16 - 10:28:18", "temp": 12, "hum": 32}, {"time": "2019/07/16 - 10:28:18", "temp": 46, "hum": 3}, {"time": "2019/07/16 - 11:16:08", "temp": 35, "hum": 62}, {"time": "2019/07/16 - 11:16:08", "temp": 23, "hum": 19}, {"time": "2019/07/16 - 11:16:08", "temp": 4, "hum": 96}, {"time": "2019/07/16 - 11:16:08", "temp": 23, "hum": 64}, {"time": "2019/07/16 - 11:16:09", "temp": 23, "hum": 64}], "12": [{"time": "2019/07/16 - 08:40:26", "temp": 5, "hum": 85}, {"time": "2019/07/16 - 08:40:35", "temp": 8, "hum": 25}, {"time": "2019/07/16 - 08:40:37", "temp": -4, "hum": 1}, {"time": "2019/07/16 - 08:40:39", "temp": -8, "hum": 88}, {"time": "2019/07/16 - 08:47:59", "temp": 9, "hum": 85}, {"time": "2019/07/16 - 10:02:59", "temp": 40, "hum": 60}, {"time": "2019/07/16 - 10:02:59", "temp": 41, "hum": 69}, {"time": "2019/07/16 - 10:02:59", "temp": 28, "hum": 31}, {"time": "2019/07/16 - 10:02:59", "temp": 34, "hum": 10}, {"time": "2019/07/16 - 10:02:59", "temp": 49, "hum": 41}, {"time": "2019/07/16 - 10:28:18", "temp": 42, "hum": 74}, {"time": "2019/07/16 - 10:28:18", "temp": 32, "hum": 70}, {"time": "2019/07/16 - 10:28:18", "temp": 39, "hum": 85}, {"time": "2019/07/16 - 10:28:18", "temp": -4, "hum": 92}, {"time": "2019/07/16 - 10:28:18", "temp": 30, "hum": 88}, {"time": "2019/07/16 - 11:16:09", "temp": 7, "hum": 31}, {"time": "2019/07/16 - 11:16:09", "temp": 18, "hum": 78}, {"time": "2019/07/16 - 11:16:09", "temp": 24, "hum": 71}, {"time": "2019/07/16 - 11:16:09", "temp": -8, "hum": 27}, {"time": "2019/07/16 - 11:16:09", "temp": 41, "hum": 54}], "13": [{"time": "2019/07/16 - 08:40:26", "temp": 33, "hum": 41}, {"time": "2019/07/16 - 08:40:35", "temp": 43, "hum": 53}, {"time": "2019/07/16 - 08:40:37", "temp": 27, "hum": 74}, {"time": "2019/07/16 - 08:40:39", "temp": 49, "hum": 30}, {"time": "2019/07/16 - 08:47:59", "temp": -6, "hum": 16}, {"time": "2019/07/16 - 10:02:59", "temp": 35, "hum": 92}, {"time": "2019/07/16 - 10:02:59", "temp": 38, "hum": 66}, {"time": "2019/07/16 - 10:02:59", "temp": 20, "hum": 71}, {"time": "2019/07/16 - 10:02:59", "temp": 20, "hum": 57}, {"time": "2019/07/16 - 10:02:59", "temp": 33, "hum": 46}, {"time": "2019/07/16 - 10:28:18", "temp": 12, "hum": 92}, {"time": "2019/07/16 - 10:28:18", "temp": -5, "hum": 57}, {"time": "2019/07/16 - 10:28:18", "temp": -7, "hum": 11}, {"time": "2019/07/16 - 10:28:18", "temp": -5, "hum": 44}, {"time": "2019/07/16 - 10:28:18", "temp": 9, "hum": 86}, {"time": "2019/07/16 - 11:16:09", "temp": 13, "hum": 81}, {"time": "2019/07/16 - 11:16:09", "temp": 18, "hum": 9}, {"time": "2019/07/16 - 11:16:09", "temp": 9, "hum": 51}, {"time": "2019/07/16 - 11:16:09", "temp": 49, "hum": 5}, {"time": "2019/07/16 - 11:16:09", "temp": -5, "hum": 89}], "14": [{"time": "2019/07/16 - 08:40:26", "temp": 34, "hum": 70}, {"time": "2019/07/16 - 08:40:35", "temp": 10, "hum": 98}, {"time": "2019/07/16 - 08:40:37", "temp": 28, "hum": 80}, {"time": "2019/07/16 - 08:40:39", "temp": 45, "hum": 77}, {"time": "2019/07/16 - 08:47:59", "temp": 2, "hum": 41}, {"time": "2019/07/16 - 10:02:59", "temp": 17, "hum": 25}, {"time": "2019/07/16 - 10:02:59", "temp": 19, "hum": 56}, {"time": "2019/07/16 - 10:02:59", "temp": 36, "hum": 77}, {"time": "2019/07/16 - 10:02:59", "temp": -3, "hum": 76}, {"time": "2019/07/16 - 10:03:00", "temp": -10, "hum": 78}, {"time": "2019/07/16 - 10:28:18", "temp": -6, "hum": 26}, {"time": "2019/07/16 - 10:28:18", "temp": 43, "hum": 10}, {"time": "2019/07/16 - 10:28:18", "temp": 10, "hum": 7}, {"time": "2019/07/16 - 10:28:18", "temp": 8, "hum": 14}, {"time": "2019/07/16 - 10:28:18", "temp": 39, "hum": 84}, {"time": "2019/07/16 - 11:16:09", "temp": 20, "hum": 2}, {"time": "2019/07/16 - 11:16:09", "temp": 40, "hum": 56}, {"time": "2019/07/16 - 11:16:09", "temp": 42, "hum": 85}, {"time": "2019/07/16 - 11:16:09", "temp": 19, "hum": 74}, {"time": "2019/07/16 - 11:16:10", "temp": 29, "hum": 78}], "15": [{"time": "2019/07/16 - 08:40:26", "temp": 13, "hum": 54}, {"time": "2019/07/16 - 08:40:35", "temp": 46, "hum": 18}, {"time": "2019/07/16 - 08:40:37", "temp": 38, "hum": 23}, {"time": "2019/07/16 - 08:40:39", "temp": 16, "hum": 48}, {"time": "2019/07/16 - 08:47:59", "temp": 28, "hum": 73}, {"time": "2019/07/16 - 10:03:00", "temp": 3, "hum": 79}, {"time": "2019/07/16 - 10:03:00", "temp": -6, "hum": 11}, {"time": "2019/07/16 - 10:03:00", "temp": 49, "hum": 81}, {"time": "2019/07/16 - 10:03:00", "temp": 24, "hum": 79}, {"time": "2019/07/16 - 10:03:00", "temp": 42, "hum": 32}, {"time": "2019/07/16 - 10:28:18", "temp": 48, "hum": 12}, {"time": "2019/07/16 - 10:28:18", "temp": 40, "hum": 61}, {"time": "2019/07/16 - 10:28:19", "temp": 0, "hum": 81}, {"time": "2019/07/16 - 10:28:19", "temp": 47, "hum": 100}, {"time": "2019/07/16 - 10:28:19", "temp": 41, "hum": 51}, {"time": "2019/07/16 - 11:16:10", "temp": 29, "hum": 26}, {"time": "2019/07/16 - 11:16:10", "temp": 36, "hum": 15}, {"time": "2019/07/16 - 11:16:10", "temp": 26, "hum": 51}, {"time": "2019/07/16 - 11:16:10", "temp": 15, "hum": 33}, {"time": "2019/07/16 - 11:16:10", "temp": 23, "hum": 57}], "16": [{"time": "2019/07/16 - 10:28:19", "temp": -1, "hum": 69}, {"time": "2019/07/16 - 10:28:19", "temp": -5, "hum": 86}, {"time": "2019/07/16 - 10:28:19", "temp": 49, "hum": 58}, {"time": "2019/07/16 - 10:28:19", "temp": 19, "hum": 5}, {"time": "2019/07/16 - 10:28:19", "temp": 42, "hum": 18}, {"time": "2019/07/16 - 11:16:10", "temp": -1, "hum": 34}, {"time": "2019/07/16 - 11:16:10", "temp": 43, "hum": 58}, {"time": "2019/07/16 - 11:16:10", "temp": 35, "hum": 53}, {"time": "2019/07/16 - 11:16:10", "temp": -5, "hum": 27}, {"time": "2019/07/16 - 11:16:10", "temp": 5, "hum": 29}]}